[
  {
    "uuid": "e1b7c9f4a2d3b8e5f6c4d7a9b3e2f8c1",
    "avatarUrl": "/assets/players/tony_adams.jpg",
    "name": "Tony Adams",
    "position": "CB",
    "playablePositions": ["CB"],
    "foot": "RIGHT",
    "rating": 88,
    "form": "GOOD",
    "fitness": 92,
    "salary": 90000,
    "contractLength": 10,
    "birthday": "1966-10-10",
    "nationality": "England",
    "height": 191,
    "weight": 86,
    "edition": "CLASSIC_90S",
    "attributes": {
      "pace": 63,
      "acceleration": 60,
      "agility": 58,
      "stamina": 82,
      "strength": 90,
      "jumping": 86,
      "dribbling": 58,
      "ballControl": 65,
      "crossing": 50,
      "shooting": 55,
      "longShots": 52,
      "reactions": 85,
      "heading": 88,
      "tackling": 94,
      "defending": 95,
      "finishing": 45,
      "shortPassing": 72,
      "longPassing": 68,
      "powerShots": 60,
      "setPieces": 50,
      "vision": 68,
      "positioning": 90,
      "anticipation": 90,
      "decisionMaking": 88,
      "composure": 85,
      "concentration": 92,
      "workRate": 86,
      "leadership": 98,
      "flair": 50,
      "creativity": 55,
      "reflexes": 5,
      "diving": 5,
      "handling": 5,
      "kicking": 5,
      "positioningGK": 5,
      "oneOnOne": 5,
      "commandOfArea": 5
    },
    "marketValue": 20000000,
    "potential": 4,
    "skillMoves": 2,
    "preferredRole": "SWEEPER",
    "personality": "DISCIPLINED",
    "injuryProne": 2,
    "consistency": 94
  },
  {
    "uuid": "b4e9d2f7a1c3e8b5d9a6f2c4e1b7a3d8",
    "avatarUrl": "/assets/players/matthias_sammer.jpg",
    "name": "Matthias Sammer",
    "position": "CB",
    "playablePositions": ["CB", "CDM", "SW"],
    "foot": "RIGHT",
    "rating": 91,
    "form": "EXCELLENT",
    "fitness": 93,
    "salary": 95000,
    "contractLength": 10,
    "birthday": "1967-09-05",
    "nationality": "Germany",
    "height": 181,
    "weight": 77,
    "edition": "CLASSIC_90S",
    "attributes": {
      "pace": 75,
      "acceleration": 74,
      "agility": 72,
      "stamina": 88,
      "strength": 84,
      "jumping": 82,
      "dribbling": 72,
      "ballControl": 78,
      "crossing": 66,
      "shooting": 70,
      "longShots": 74,
      "reactions": 88,
      "heading": 80,
      "tackling": 92,
      "defending": 94,
      "finishing": 65,
      "shortPassing": 82,
      "longPassing": 80,
      "powerShots": 72,
      "setPieces": 65,
      "vision": 80,
      "positioning": 88,
      "anticipation": 92,
      "decisionMaking": 90,
      "composure": 88,
      "concentration": 90,
      "workRate": 86,
      "leadership": 92,
      "flair": 68,
      "creativity": 75,
      "reflexes": 5,
      "diving": 5,
      "handling": 5,
      "kicking": 5,
      "positioningGK": 5,
      "oneOnOne": 5,
      "commandOfArea": 5
    },
    "marketValue": 30000000,
    "potential": 5,
    "skillMoves": 3,
    "preferredRole": "SWEEPER",
    "personality": "DISCIPLINED",
    "injuryProne": 3,
    "consistency": 93
  },
  {
    "uuid": "c7f4a9b1d2e8f3a6b5c1d9a7f2b4e6c3",
    "avatarUrl": "/assets/players/emmanuel_petit.jpg",
    "name": "Emmanuel Petit",
    "position": "CDM",
    "playablePositions": ["CDM", "CM", "LB"],
    "foot": "LEFT",
    "rating": 86,
    "form": "GOOD",
    "fitness": 90,
    "salary": 85000,
    "contractLength": 10,
    "birthday": "1970-09-22",
    "nationality": "France",
    "height": 185,
    "weight": 79,
    "edition": "CLASSIC_90S",
    "attributes": {
      "pace": 72,
      "acceleration": 70,
      "agility": 70,
      "stamina": 88,
      "strength": 84,
      "jumping": 78,
      "dribbling": 70,
      "ballControl": 76,
      "crossing": 68,
      "shooting": 74,
      "longShots": 80,
      "reactions": 82,
      "heading": 75,
      "tackling": 88,
      "defending": 89,
      "finishing": 62,
      "shortPassing": 80,
      "longPassing": 82,
      "powerShots": 80,
      "setPieces": 70,
      "vision": 76,
      "positioning": 84,
      "anticipation": 85,
      "decisionMaking": 83,
      "composure": 84,
      "concentration": 84,
      "workRate": 86,
      "leadership": 80,
      "flair": 60,
      "creativity": 70,
      "reflexes": 5,
      "diving": 5,
      "handling": 5,
      "kicking": 5,
      "positioningGK": 5,
      "oneOnOne": 5,
      "commandOfArea": 5
    },
    "marketValue": 18000000,
    "potential": 4,
    "skillMoves": 2,
    "preferredRole": "BOX_TO_BOX",
    "personality": "DISCIPLINED",
    "injuryProne": 2,
    "consistency": 88
  },
  {
    "uuid": "b3a7c9e2d4f6a1b8c2e5f9d7a4b6c3e8",
    "avatarUrl": "/assets/players/franco_baresi.jpg",
    "name": "Franco Baresi",
    "position": "CB",
    "playablePositions": ["CB", "SW"],
    "foot": "RIGHT",
    "rating": 94,
    "form": "EXCELLENT",
    "fitness": 100,
    "salary": 130000,
    "contractLength": 16,
    "birthday": "1960-05-08",
    "nationality": "Italy",
    "height": 176,
    "weight": 70,
    "edition": "CLASSIC_90S",
    "attributes": {
      "pace": 76,
      "acceleration": 74,
      "agility": 78,
      "stamina": 86,
      "strength": 80,
      "jumping": 82,
      "dribbling": 68,
      "ballControl": 80,
      "crossing": 55,
      "shooting": 50,
      "longShots": 55,
      "reactions": 92,
      "heading": 78,
      "tackling": 96,
      "defending": 97,
      "finishing": 45,
      "shortPassing": 80,
      "longPassing": 78,
      "powerShots": 50,
      "setPieces": 52,
      "vision": 82,
      "positioning": 94,
      "anticipation": 97,
      "decisionMaking": 95,
      "composure": 96,
      "concentration": 95,
      "workRate": 88,
      "leadership": 98,
      "flair": 50,
      "creativity": 65,
      "reflexes": 5,
      "diving": 5,
      "handling": 5,
      "kicking": 5,
      "positioningGK": 5,
      "oneOnOne": 5,
      "commandOfArea": 5
    },
    "marketValue": 42000000,
    "potential": 5,
    "skillMoves": 2,
    "preferredRole": "SWEEPER",
    "personality": "DISCIPLINED",
    "injuryProne": 1,
    "consistency": 97
  }
]
